CHANGELOG.md
README.md
setup.py
aio_gnutls_transport/__init__.py
aio_gnutls_transport/_gnutls_build.py
aio_gnutls_transport/ssl.py
aio_gnutls_transport/stdlib.py
aio_gnutls_transport.egg-info/PKG-INFO
aio_gnutls_transport.egg-info/SOURCES.txt
aio_gnutls_transport.egg-info/dependency_links.txt
aio_gnutls_transport.egg-info/requires.txt
aio_gnutls_transport.egg-info/top_level.txt
test/test_common.py
test/test_gnutls_context.py
test/test_gnutls_transport.py