Metadata-Version: 2.1
Name: aio-gnutls-transport
Version: 0.3.0
Summary: asyncio transport over GnuTLS
Home-page: https://gitlab.inria.fr/abaire/aio_gnutls_transport/
Author: Anthony Baire
Author-email: Anthony.Baire@irisa.fr
License: LGPL2.1+
Keywords: asyncio,TLS,transport,GnuTLS
Platform: linux
Classifier: Development Status :: 4 - Beta
Classifier: Framework :: AsyncIO
Classifier: License :: OSI Approved :: GNU Lesser General Public License v2 or later (LGPLv2+)
Classifier: Operating System :: POSIX :: Linux
Classifier: Programming Language :: Python :: 3.6
Classifier: Programming Language :: Python :: 3.7
Classifier: Programming Language :: Python :: 3.8
Classifier: Topic :: Security :: Cryptography
